LICENSE
MANIFEST.in
README.txt
setup.py
OASYS1_ALS_ShadowOui.egg-info/PKG-INFO
OASYS1_ALS_ShadowOui.egg-info/SOURCES.txt
OASYS1_ALS_ShadowOui.egg-info/dependency_links.txt
OASYS1_ALS_ShadowOui.egg-info/entry_points.txt
OASYS1_ALS_ShadowOui.egg-info/namespace_packages.txt
OASYS1_ALS_ShadowOui.egg-info/not-zip-safe
OASYS1_ALS_ShadowOui.egg-info/requires.txt
OASYS1_ALS_ShadowOui.egg-info/top_level.txt
orangecontrib/__init__.py
orangecontrib/shadow/__init__.py
orangecontrib/shadow/als/__init__.py
orangecontrib/shadow/als/util/__init__.py
orangecontrib/shadow/als/util/enhanced_grid.py
orangecontrib/shadow/als/util/fast_grid.py
orangecontrib/shadow/als/util/gradient.py
orangecontrib/shadow/als/util/image.py
orangecontrib/shadow/als/util/random_distributions.py
orangecontrib/shadow/als/util/random_image.py
orangecontrib/shadow/als/util/test_sampling_srio.py
orangecontrib/shadow/als/widgets/__init__.py
orangecontrib/shadow/als/widgets/gui/__init__.py
orangecontrib/shadow/als/widgets/gui/ow_als_generic_analyzer.py
orangecontrib/shadow/als/widgets/gui/ow_als_shadow_widget.py
orangecontrib/shadow/als/widgets/gui/plots.py
orangecontrib/shadow/als/widgets/gui/shadow4_ow_automatic_element.py
orangecontrib/shadow/als/widgets/gui/shadow4_ow_electron_beam.py
orangecontrib/shadow/als/widgets/gui/shadow4_ow_generic_element.py
orangecontrib/shadow/als/widgets/gui/shadow4_plots.py
orangecontrib/shadow/als/widgets/gui/shadow4_python_script.py
orangecontrib/shadow/als/widgets/utility/__init__.py
orangecontrib/shadow/als/widgets/utility/ow_als_caustic.py
orangecontrib/shadow/als/widgets/utility/ow_als_curved_element_analyzer.py
orangecontrib/shadow/als/widgets/utility/ow_als_grating_analyzer.py
orangecontrib/shadow/als/widgets/utility/ow_als_resolving_power.py
orangecontrib/shadow/als/widgets/utility/ow_als_slit_integrator.py
orangecontrib/shadow/als/widgets/utility/ow_als_undulator.py
orangecontrib/shadow/als/widgets/utility/ow_als_wavefront_generator.py
orangecontrib/shadow/als/widgets/utility/ow_als_wiggler.py
orangecontrib/shadow/als/widgets/utility/icons/caustic.png
orangecontrib/shadow/als/widgets/utility/icons/curved_element_analyzer.png
orangecontrib/shadow/als/widgets/utility/icons/grating_analyzer.png
orangecontrib/shadow/als/widgets/utility/icons/integral.png
orangecontrib/shadow/als/widgets/utility/icons/lbl.png
