Metadata-Version: 2.1
Name: OASYS1-ALS-ShadowOui
Version: 0.0.59
Summary: WIDGETS DEVELOPED FOR ALS TO EXTEND OASYS FUNCTIONALITIES
Home-page: https://github.com/oasys-als-kit/OASYS1-ALS-ShadowOui
Author: Luca Rebuffi and Antoine Wojdyla and Manuel Sanchez del Rio
Author-email: awojdyla@lbl.gov, srio@lbl.gov
License: MIT
Download-URL: https://github.com/oasys-als-kit/OASYS1-ALS-ShadowOui
Keywords: ray-tracing,simulator,oasys1
Platform: UNKNOWN
Classifier: Development Status :: 4 - Beta
Classifier: Environment :: X11 Applications :: Qt
Classifier: Environment :: Console
Classifier: Environment :: Plugins
Classifier: Programming Language :: Cython
Classifier: Programming Language :: Python
Classifier: Programming Language :: Python :: 3
Classifier: Intended Audience :: Science/Research
License-File: LICENSE
